[{"region_id": "3237971", "title_ru": "Judeţul Galaţi"}, {"region_id": "3237435", "title_ru": "Judeţul Giurgiu"}, {"region_id": "3232689", "title_ru": "Judeţul Olt"}, {"region_id": "3229400", "title_ru": "Judeţul Sălaj"}, {"region_id": "3227213", "title_ru": "Judeţul Suceava"}, {"region_id": "3237252", "title_ru": "Judeţul Gorj"}, {"region_id": "3224506", "title_ru": "Judeţul Vâlcea"}, {"region_id": "3224713", "title_ru": "Judeţul Vaslui"}, {"region_id": "3236708", "title_ru": "Judeţul Harghita"}, {"region_id": "3245653", "title_ru": "Judeţul Argeş"}, {"region_id": "3243727", "title_ru": "Judeţul Botoşani"}, {"region_id": "3243553", "title_ru": "Judeţul Braşov"}, {"region_id": "3241249", "title_ru": "Judeţul Cluj"}, {"region_id": "3240457", "title_ru": "Judeţul Covasna"}, {"region_id": "3239507", "title_ru": "Judeţul Dâmboviţa"}, {"region_id": "3239288", "title_ru": "Judeţul Dolj"}, {"region_id": "3236360", "title_ru": "Judeţul Hunedoara"}, {"region_id": "3236301", "title_ru": "Judeţul Ialomiţa"}, {"region_id": "3246003", "title_ru": "Judeţul Alba"}, {"region_id": "3245707", "title_ru": "Judeţul Arad"}, {"region_id": "3244474", "title_ru": "Judeţul Bihor"}, {"region_id": "3243605", "title_ru": "Judeţul Brăila"}, {"region_id": "3242895", "title_ru": "Judeţul Buzău"}, {"region_id": "3243238", "title_ru": "Municipiul Bucureşti"}, {"region_id": "3242544", "title_ru": "Judeţul Caraş-Severin"}, {"region_id": "3240946", "title_ru": "Judeţul Constanţa"}, {"region_id": "3230737", "title_ru": "Judeţul Prahova"}, {"region_id": "3229052", "title_ru": "Judeţul Satu Mare"}, {"region_id": "3228505", "title_ru": "Judeţul Sibiu"}, {"region_id": "3226724", "title_ru": "Judeţul Teleorman"}, {"region_id": "3226552", "title_ru": "Judeţul Timiş"}, {"region_id": "3226035", "title_ru": "Judeţul Tulcea"}, {"region_id": "3245431", "title_ru": "Judeţul Bacău"}, {"region_id": "3244278", "title_ru": "Judeţul Bistriţa-Năsăud"}, {"region_id": "3242802", "title_ru": "Judeţul Călăraşi"}, {"region_id": "3236267", "title_ru": "Judeţul Iaşi"}, {"region_id": "3314752", "title_ru": "Judeţul Ilfov"}, {"region_id": "3234506", "title_ru": "Judeţul Maramureş"}, {"region_id": "3234262", "title_ru": "Judeţul Mehedinţi"}, {"region_id": "3233372", "title_ru": "Judeţul Mureş"}, {"region_id": "3233232", "title_ru": "Judeţul Neamţ"}, {"region_id": "3224105", "title_ru": "Judeţul Vrancea"}]