[{"region_id": "3395905", "title_ru": "Bulawayo Province"}, {"region_id": "3395906", "title_ru": "Harare Province"}, {"region_id": "3317072", "title_ru": "Manicaland Province"}, {"region_id": "3317049", "title_ru": "Mashonaland Central Province"}, {"region_id": "3317048", "title_ru": "Mashonaland East Province"}, {"region_id": "3317047", "title_ru": "Mashonaland West Province"}, {"region_id": "3317042", "title_ru": "Masvingo Province"}, {"region_id": "3317040", "title_ru": "Matabeleland North Province"}, {"region_id": "3317039", "title_ru": "Matabeleland South Province"}, {"region_id": "3316993", "title_ru": "Midlands Province"}]